[
  {
    "name": "Psycho Killer - 2005 Remaster",
    "album_name": "Talking Heads 77 (Deluxe Version)"
  },
  {
    "name": "This Must Be the Place (Naive Melody) - 2005 Remaster",
    "album_name": "Speaking In Tongues (Deluxe Version)"
  },
  {
    "name": "Once in a Lifetime - 2005 Remaster",
    "album_name": "Remain In Light (Deluxe Version)"
  },
  {
    "name": "Burning Down the House - 45 Version",
    "album_name": "Burning Down The House / I Get Wild/Wild Gravity [Digital 45]"
  },
  {
    "name": "Road to Nowhere - 2005 Remaster",
    "album_name": "Little Creatures"
  },
  {
    "name": "Born Under Punches (The Heat Goes On) - 2005 Remaster",
    "album_name": "Remain In Light (Deluxe Version)"
  },
  {
    "name": "And She Was - 2005 Remaster",
    "album_name": "Little Creatures"
  },
  {
    "name": "Slippery People - Live",
    "album_name": "Stop Making Sense"
  },
  {
    "name": "Psycho Killer - Acoustic",
    "album_name": "Talking Heads 77 (Deluxe Version)"
  },
  {
    "name": "Sugar on My Tongue - 2005 Remaster",
    "album_name": "Talking Heads 77 (Deluxe Version)"
  },
  {
    "name": "This Must Be the Place (Naive Melody) - Live",
    "album_name": "Stop Making Sense"
  },
  {
    "name": "Burning Down the House - 2005 Remaster",
    "album_name": "Speaking In Tongues (Deluxe Version)"
  },
  {
    "name": "Crosseyed and Painless - 2005 Remaster",
    "album_name": "Remain In Light (Deluxe Version)"
  },
  {
    "name": "Psycho Killer - Live",
    "album_name": "Stop Making Sense"
  },
  {
    "name": "Moon Rocks - 2005 Remaster",
    "album_name": "Speaking In Tongues (Deluxe Version)"
  },
  {
    "name": "Psycho Killer",
    "album_name": "Popular Favorites 1976-1992: Sand In The Vaseline"
  },
  {
    "name": "Wild Wild Life - Remastered",
    "album_name": "The Best Of Talking Heads"
  },
  {
    "name": "(Nothing But) Flowers - Remastered",
    "album_name": "The Best Of Talking Heads"
  },
  {
    "name": "The Lady Don't Mind - 2005 Remaster",
    "album_name": "Little Creatures"
  },
  {
    "name": "Heaven - Live",
    "album_name": "Stop Making Sense"
  },
  {
    "name": "Girlfriend Is Better - Live",
    "album_name": "Stop Making Sense"
  },
  {
    "name": "The Great Curve - 2005 Remaster",
    "album_name": "Remain In Light (Deluxe Version)"
  },
  {
    "name": "Uh-Oh, Love Comes to Town - 2005 Remaster",
    "album_name": "Talking Heads 77 (Deluxe Version)"
  },
  {
    "name": "Pulled Up - 2005 Remaster",
    "album_name": "Talking Heads 77 (Deluxe Version)"
  },
  {
    "name": "Burning Down the House - Live",
    "album_name": "Stop Making Sense"
  },
  {
    "name": "Girlfriend Is Better - 2005 Remaster",
    "album_name": "Speaking In Tongues (Deluxe Version)"
  },
  {
    "name": "Slippery People - 2005 Remaster",
    "album_name": "Speaking In Tongues (Deluxe Version)"
  },
  {
    "name": "Life During Wartime - Live",
    "album_name": "Stop Making Sense"
  },
  {
    "name": "Pull up the Roots - 2005 Remaster",
    "album_name": "Speaking In Tongues (Deluxe Version)"
  },
  {
    "name": "Houses in Motion - 2005 Remaster",
    "album_name": "Remain In Light (Deluxe Version)"
  },
  {
    "name": "(Nothing But) Flowers - 2005 Remaster",
    "album_name": "Naked [w/Bonus Track]"
  },
  {
    "name": "Thank You for Sending Me an Angel - Live",
    "album_name": "Stop Making Sense"
  },
  {
    "name": "Once in a Lifetime - Live",
    "album_name": "Stop Making Sense"
  },
  {
    "name": "Genius of Love (Tom Tom Club) - Live",
    "album_name": "Stop Making Sense"
  },
  {
    "name": "Burning Down the House",
    "album_name": "Speaking In Tongues"
  },
  {
    "name": "The Book I Read - 2005 Remaster",
    "album_name": "Talking Heads 77 (Deluxe Version)"
  },
  {
    "name": "Once in a Lifetime - Remastered",
    "album_name": "The Best Of Talking Heads"
  },
  {
    "name": "This Must Be the Place (Naive Melody) - Remastered",
    "album_name": "The Best Of Talking Heads"
  },
  {
    "name": "Making Flippy Floppy - 2005 Remaster",
    "album_name": "Speaking In Tongues (Deluxe Version)"
  },
  {
    "name": "Two Note Swivel - Unfinished Outtake",
    "album_name": "Speaking In Tongues (Deluxe Version)"
  },
  {
    "name": "Listening Wind - 2005 Remaster",
    "album_name": "Remain In Light (Deluxe Version)"
  },
  {
    "name": "New Feeling - 2005 Remaster",
    "album_name": "Talking Heads 77 (Deluxe Version)"
  },
  {
    "name": "Road to Nowhere - Remastered",
    "album_name": "The Best Of Talking Heads"
  },
  {
    "name": "(Nothing But) Flowers",
    "album_name": "Naked"
  },
  {
    "name": "Wild Wild Life - 2005 Remaster",
    "album_name": "True Stories"
  },
  {
    "name": "Found a Job - Live",
    "album_name": "Stop Making Sense"
  },
  {
    "name": "What a Day That Was - Live Edit",
    "album_name": "Stop Making Sense"
  },
  {
    "name": "Take Me to the River - Live",
    "album_name": "Stop Making Sense"
  },
  {
    "name": "I Get Wild / Wild Gravity - 2005 Remaster",
    "album_name": "Speaking In Tongues (Deluxe Version)"
  },
  {
    "name": "Once in a Lifetime",
    "album_name": "Remain In Light"
  }
]